{
  "records": [
    {
      "username": "admin",
      "password": "d0970714757783e6cf17b26fb8e2298f",
      "id": 1,
      "lastLoginTime": 1605863447474,
      "errorTimes": 0,
      "updateOn": 1605863447475,
      "updateBy": "admin",
      "permissionType": 30,
      "nickname": "ee"
    },
    {
      "username": "xiaoming",
      "password": "d0970714757783e6cf17b26fb8e2298f",
      "id": 1602306639695,
      "createOn": 1602306639695,
      "errorTimes": 0,
      "updateOn": 1605690294851,
      "updateBy": "xiaoming",
      "deleted": false,
      "lastLoginTime": 1605690291062,
      "nickname": "ttt"
    },
    {
      "username": "liuzi",
      "password": "112233",
      "id": 1602431998492,
      "createOn": 1602431998492,
      "createBy": "admin",
      "errorTimes": 2
    },
    {
      "username": "zg",
      "password": "112233",
      "id": 1605081463265,
      "createOn": 1605081463266,
      "createBy": "admin"
    },
    {
      "username": "user1",
      "password": "d0970714757783e6cf17b26fb8e2298f",
      "id": 1605590031484,
      "createOn": 1605590031484,
      "createBy": "admin",
      "nickname": "1",
      "updateOn": 1605770085643,
      "updateBy": "admin"
    },
    {
      "username": "user2",
      "password": "d0970714757783e6cf17b26fb8e2298f",
      "id": 1605590037571,
      "createOn": 1605590037571,
      "createBy": "admin"
    },
    {
      "username": "user3",
      "password": "d0970714757783e6cf17b26fb8e2298f",
      "id": 1605590041905,
      "createOn": 1605590041905,
      "createBy": "admin"
    },
    {
      "username": "user4",
      "password": "d0970714757783e6cf17b26fb8e2298f",
      "id": 1605590045556,
      "createOn": 1605590045556,
      "createBy": "admin"
    },
    {
      "username": "user5",
      "password": "d0970714757783e6cf17b26fb8e2298f",
      "id": 1605590049105,
      "createOn": 1605590049105,
      "createBy": "admin"
    },
    {
      "username": "user6",
      "password": "d0970714757783e6cf17b26fb8e2298f",
      "id": 1605590053542,
      "createOn": 1605590053542,
      "createBy": "admin"
    },
    {
      "username": "user7",
      "password": "d0970714757783e6cf17b26fb8e2298f",
      "id": 1605590057080,
      "createOn": 1605590057080,
      "createBy": "admin"
    },
    {
      "username": "user8",
      "password": "d0970714757783e6cf17b26fb8e2298f",
      "id": 1605590060593,
      "createOn": 1605590060593,
      "createBy": "admin"
    },
    {
      "username": "user9",
      "password": "d0970714757783e6cf17b26fb8e2298f",
      "id": 1605590064012,
      "createOn": 1605590064012,
      "createBy": "admin"
    },
    {
      "username": "user10",
      "password": "d0970714757783e6cf17b26fb8e2298f",
      "id": 1605590069077,
      "createOn": 1605590069077,
      "createBy": "admin"
    },
    {
      "username": "user11",
      "password": "d0970714757783e6cf17b26fb8e2298f",
      "id": 1605590072098,
      "createOn": 1605590072098,
      "createBy": "admin"
    },
    {
      "username": "user12",
      "password": "d0970714757783e6cf17b26fb8e2298f",
      "id": 1605590075068,
      "createOn": 1605590075068,
      "createBy": "admin"
    },
    {
      "username": "user13",
      "password": "d0970714757783e6cf17b26fb8e2298f",
      "id": 1605590078309,
      "createOn": 1605590078309,
      "createBy": "admin",
      "nickname": "13",
      "updateOn": 1605689260432,
      "updateBy": "admin"
    },
    {
      "username": "user14",
      "password": "d0970714757783e6cf17b26fb8e2298f",
      "id": 1605590081926,
      "createOn": 1605590081926,
      "createBy": "admin"
    },
    {
      "username": "user15",
      "password": "d0970714757783e6cf17b26fb8e2298f",
      "id": 1605590085029,
      "createOn": 1605590085029,
      "createBy": "admin"
    },
    {
      "username": "user16",
      "password": "d0970714757783e6cf17b26fb8e2298f",
      "id": 1605590088695,
      "createOn": 1605590088695,
      "createBy": "admin"
    },
    {
      "username": "user17",
      "password": "d0970714757783e6cf17b26fb8e2298f",
      "id": 1605590092021,
      "createOn": 1605590092021,
      "createBy": "admin"
    },
    {
      "username": "user18",
      "password": "d0970714757783e6cf17b26fb8e2298f",
      "id": 1605590095147,
      "createOn": 1605590095147,
      "createBy": "admin"
    },
    {
      "username": "user19",
      "password": "d0970714757783e6cf17b26fb8e2298f",
      "id": 1605590099988,
      "createOn": 1605590099988,
      "createBy": "admin"
    }
  ]
}